MF_Algebra/__init__.py
MF_Algebra/actions/__init__.py
MF_Algebra/actions/action_core.py
MF_Algebra/actions/animations.py
MF_Algebra/actions/apply_operation.py
MF_Algebra/actions/evaluation.py
MF_Algebra/actions/parallel.py
MF_Algebra/actions/permutations.py
MF_Algebra/actions/substitution.py
MF_Algebra/actions/variants.py
MF_Algebra/algebra/__init__.py
MF_Algebra/algebra/algebra_core.py
MF_Algebra/algebra/distribution.py
MF_Algebra/algebra/equations.py
MF_Algebra/algebra/factoring.py
MF_Algebra/algebra/simplify.py
MF_Algebra/calculus/__init__.py
MF_Algebra/calculus/differentials.py
MF_Algebra/calculus/differentiation.py
MF_Algebra/calculus/integrals.py
MF_Algebra/calculus/integration.py
MF_Algebra/calculus/limits.py
MF_Algebra/calculus/series.py
MF_Algebra/expressions/__init__.py
MF_Algebra/expressions/combiners/__init__.py
MF_Algebra/expressions/combiners/combiners.py
MF_Algebra/expressions/combiners/operations.py
MF_Algebra/expressions/combiners/relations.py
MF_Algebra/expressions/combiners/scripts.py
MF_Algebra/expressions/combiners/sequences.py
MF_Algebra/expressions/expression_core.py
MF_Algebra/expressions/functions/__init__.py
MF_Algebra/expressions/functions/functions.py
MF_Algebra/expressions/functions/logarithms.py
MF_Algebra/expressions/functions/miscellaneous.py
MF_Algebra/expressions/functions/operators.py
MF_Algebra/expressions/functions/radicals.py
MF_Algebra/expressions/numbers/__init__.py
MF_Algebra/expressions/numbers/complex.py
MF_Algebra/expressions/numbers/integer.py
MF_Algebra/expressions/numbers/number.py
MF_Algebra/expressions/numbers/rational.py
MF_Algebra/expressions/numbers/real.py
MF_Algebra/expressions/variables.py
MF_Algebra/sets/__init__.py
MF_Algebra/sets/intervals.py
MF_Algebra/sets/set_core.py
MF_Algebra/sets/set_operations.py
MF_Algebra/timelines/__init__.py
MF_Algebra/timelines/timeline_common.py
MF_Algebra/timelines/timeline_core.py
MF_Algebra/timelines/timeline_variants.py
MF_Algebra/trigonometry/__init__.py
mf_algebra-0.5.5.dist-info/LICENSE.md
mf_algebra-0.5.5.dist-info/METADATA
mf_algebra-0.5.5.dist-info/WHEEL
mf_algebra-0.5.5.dist-info/RECORD
