Metadata-Version: 2.3
Name: MF-Algebra
Version: 0.5.5
Summary: Manim plugin which aims to make it much easier to meaningfully transform algebra expressions.
License: None
Author: John Connell
Author-email: johnconnelltutor@gmail.com
Requires-Python: >=3.8
Classifier: License :: Other/Proprietary License
Classifier: Programming Language :: Python :: 3
Classifier: Programming Language :: Python :: 3.8
Classifier: Programming Language :: Python :: 3.9
Classifier: Programming Language :: Python :: 3.10
Classifier: Programming Language :: Python :: 3.11
Classifier: Programming Language :: Python :: 3.12
Classifier: Programming Language :: Python :: 3.13
Provides-Extra: manimce
Provides-Extra: manimgl
Requires-Dist: MF_Tools (>=1.4.3)
Requires-Dist: dill (>=0.4,<0.5)
Requires-Dist: manim (>=0.17.0) ; extra == "manimce"
Requires-Dist: manimgl (>=1.7.0) ; extra == "manimgl"
Requires-Dist: numpy (>=2.0)
Requires-Dist: sympy[latex] (>=1.8)
Requires-Dist: tabulate (>=0.9,<0.10)
Project-URL: Repository, https://github.com/TheMathematicFanatic/MF_Algebra
